clumo.py
clumo-0.1.0.dist-info/licenses/LICENSE.txt
clumo-0.1.0.dist-info/METADATA
clumo-0.1.0.dist-info/WHEEL
clumo-0.1.0.dist-info/top_level.txt
clumo-0.1.0.dist-info/RECORD
