Metadata-Version: 2.4
Name: clumo
Version: 0.1.0
Summary: CluMo: Clustering-based Motif Discovery from Deep Learning Models
Author-email: Your Name <your.email@example.com>
License: BSD-3-Clause
Classifier: Programming Language :: Python :: 3
Classifier: License :: OSI Approved :: BSD License
Classifier: Operating System :: OS Independent
Classifier: Topic :: Scientific/Engineering :: Bio-Informatics
Classifier: Intended Audience :: Science/Research
Requires-Python: ==3.9.7
License-File: LICENSE.txt
Requires-Dist: numpy==1.26.4
Requires-Dist: pandas==2.2.3
Requires-Dist: matplotlib==3.9.4
Requires-Dist: torch==2.0.1+cu118
Requires-Dist: scikit-learn==1.2.2
Requires-Dist: captum==0.6.0
Requires-Dist: seaborn==0.12.2
Requires-Dist: scipy==1.10.1
Requires-Dist: logomaker==0.8
Dynamic: license-file
